Workbook

Sheet Assumptions
A1: Item | B1: Value
A2: Ticket Price | B2: 10
A3: Expected Attendance | B3: 60
A4: Number of Sponsors | B4: 3
A5: Avg Sponsor Amount | B5: 500
A6: Food per Attendee | B6: 8
A7: Marketing Budget | B7: 300
A8: Venue Cost | B8: 500
A9: Equipment Cost | B9: 200

Sheet Revenue
A1: Description | B1: Amount
A2: Ticket Revenue | B2: =Assumptions!B2 * Assumptions!B3 -> 600
A3: Sponsorship Revenue | B3: =Assumptions!B3*Assumptions!B4 -> 180
A4: Total Revenue | B4: =SUM(B2:B3) -> 780

Sheet Costs
A1: Description | B1: Amount
A2: Food (variable) | B2: =Assumptions!B6*Assumptions!B3 -> 480
A3: Marketing (fixed) | B3: =Assumptions!B7 -> 300
A4: Venue (fixed) | B4: =Assumptions!B8 -> 500
A5: Equipment (fixed) | B5: =Assumptions!B9 -> 200
A6: Total Costs | B6: =SUM(B2:B5) -> 1480

Sheet Summary
A1: Metric | B1: Value
A2: Total Revenue | B2: =Revenue!B4 -> 780
A3: Total Costs | B3: =Costs!B6 -> 1480
A4: Net Surplus (Revenue - Costs) | B4: =B2-B3 -> -700
A5: Break-even Attendance (approx) | B5: =CEILING((Costs!B6-Revenue!B3)/Assumptions!#REF!,1) -> #REF!

Sheet Scenarios
A1: Scenario | B1: Attendance | C1: Num_Sponsors | D1: Ticket Revenue | E1: Sponsorship Revenue | F1: Total Revenue | G1: Variable Costs | H1: Fixed Costs | I1: Total Costs | J1: Net Surplus
A2: Conservative | B2: 40 | C2: 2 | D2: =Assumptions!$B$2 * B2 -> 400 | E2: =C2*Assumptions!$B$5 -> 1000 | F2: =D2+E2 -> 1400 | G2: =Assumptions!$B$6*B2 -> 320 | H2: =Assumptions!$B$6+Assumptions!B7+Assumptions!B8 -> 808 | I2: =G2+H2 -> 1128 | J2: =F2-I2 -> 272
A3: Expected | B3: 60 | C3: 3 | D3: =Assumptions!$B$2 * B3 -> 600 | E3: =C3*Assumptions!$B$5 -> 1500 | F3: =D3+E3 -> 2100 | G3: =Assumptions!$B$6*B3 -> 480 | H3: =Assumptions!$B$6+Assumptions!B8+Assumptions!B9 -> 708 | I3: =G3+H3 -> 1188 | J3: =F3-I3 -> 912
A4: Aggressive | B4: 80 | C4: 4 | D4: =Assumptions!$B$2 * B4 -> 800 | E4: =C4*Assumptions!$B$5 -> 2000 | F4: =D4+E4 -> 2800 | G4: =Assumptions!$B$6*B4 -> 640 | H4: =Assumptions!$B$6+Assumptions!B9+Assumptions!B10 -> 208 | I4: =G4+H4 -> 848 | J4: =F4-I4 -> 1952
D7: Ticket Revenue = Ticket Price * Attendance | E7: Sponsorship Revenue = Number of Sponsors * Average Sponsor Contribution | F7: Total Revenue = Ticket Revenue + Sponsorship Revenue
